MANIFEST.in
README.rst
setup.cfg
setup.py
ckanext/__init__.py
ckanext/datasetversions/__init__.py
ckanext/datasetversions/helpers.py
ckanext/datasetversions/plugin.py
ckanext/datasetversions/logic/__init__.py
ckanext/datasetversions/logic/action/__init__.py
ckanext/datasetversions/logic/action/create.py
ckanext/datasetversions/logic/action/get.py
ckanext/datasetversions/templates/package/read.html
ckanext/datasetversions/templates/package/read_base.html
ckanext/datasetversions/tests/__init__.py
ckanext/datasetversions/tests/helpers.py
ckanext/datasetversions/tests/test_helpers.py
ckanext/datasetversions/tests/logic/__init__.py
ckanext/datasetversions/tests/logic/action/__init__.py
ckanext/datasetversions/tests/logic/action/test_create.py
ckanext/datasetversions/tests/logic/action/test_get.py
ckanext_datasetversions.egg-info/PKG-INFO
ckanext_datasetversions.egg-info/SOURCES.txt
ckanext_datasetversions.egg-info/dependency_links.txt
ckanext_datasetversions.egg-info/entry_points.txt
ckanext_datasetversions.egg-info/pbr.json
ckanext_datasetversions.egg-info/top_level.txt