Metadata-Version: 1.1
Name: ckanext-datasetversions
Version: 1.0.1
Summary: CKAN extension to support different versions of a dataset
Home-page: https://github.com/aptivate/ckanext-datasetversions
Author: Aptivate
Author-email: mapaction-team@aptivate.org
License: AGPL
Keywords: CKAN dataset versions
Platform: UNKNOWN
Classifier: Development Status :: 4 - Beta
Classifier: License :: OSI Approved :: GNU Affero General Public License v3 or later (AGPLv3+)
Classifier: Programming Language :: Python :: 2.6
Classifier: Programming Language :: Python :: 2.7
